pelican/plugins/seo/__init__.py
pelican/plugins/seo/seo.py
pelican/plugins/seo/seo_enhancer/__init__.py
pelican/plugins/seo/seo_enhancer/html_enhancer/__init__.py
pelican/plugins/seo/seo_enhancer/html_enhancer/article_schema_creator.py
pelican/plugins/seo/seo_enhancer/html_enhancer/breadcrumb_schema_creator.py
pelican/plugins/seo/seo_enhancer/html_enhancer/canonical_url_creator.py
pelican/plugins/seo/seo_enhancer/html_enhancer/open_graph.py
pelican/plugins/seo/seo_enhancer/html_enhancer/twitter_cards.py
pelican/plugins/seo/seo_enhancer/robots_file_creator.py
pelican/plugins/seo/seo_report/__init__.py
pelican/plugins/seo/seo_report/seo_analyzer/__init__.py
pelican/plugins/seo/seo_report/seo_analyzer/content_title_analyzer.py
pelican/plugins/seo/seo_report/seo_analyzer/internal_link_analyzer.py
pelican/plugins/seo/seo_report/seo_analyzer/page_description_analyzer.py
pelican/plugins/seo/seo_report/seo_analyzer/page_title_analyzer.py
pelican/plugins/seo/seo_report/static/seo_report.css
pelican/plugins/seo/seo_report/template/seo_report.html
pelican/plugins/seo/settings.py
pelican/plugins/seo/tests/__init__.py
pelican/plugins/seo/tests/conftest.py
pelican/plugins/seo/tests/test_article_schema_creator.py
pelican/plugins/seo/tests/test_breadcrumb_schema_creator.py
pelican/plugins/seo/tests/test_canonical_url_creator.py
pelican/plugins/seo/tests/test_content_title_analyzer.py
pelican/plugins/seo/tests/test_internal_link_analyzer.py
pelican/plugins/seo/tests/test_open_graph.py
pelican/plugins/seo/tests/test_page_description_analyzer.py
pelican/plugins/seo/tests/test_page_title_analyzer.py
pelican/plugins/seo/tests/test_robots_file_creator.py
pelican/plugins/seo/tests/test_run_robots_file.py
pelican/plugins/seo/tests/test_seo_enhancer.py
pelican/plugins/seo/tests/test_seo_report.py
pelican/plugins/seo/tests/test_settings.py
pelican/plugins/seo/tests/test_twitter_cards.py
pelican_seo-1.4.0.dist-info/METADATA
pelican_seo-1.4.0.dist-info/WHEEL
pelican_seo-1.4.0.dist-info/entry_points.txt
pelican_seo-1.4.0.dist-info/RECORD
