Metadata-Version: 2.1
Name: pelican-seo
Version: 1.4.0
Summary: Pelican plugin to improve search engine optimization (SEO)
Keywords: pelican,plugin,seo,search,optimization
Author-Email: =?utf-8?q?Ma=C3=ABva_Brunelles?= <contact@tremacorp.fr>, Justin Mayer <entroP@gmail.com>
License: AGPL-3.0
Classifier: Development Status :: 5 - Production/Stable
Classifier: Environment :: Console
Classifier: Framework :: Pelican
Classifier: Framework :: Pelican :: Plugins
Classifier: Intended Audience :: End Users/Desktop
Classifier: License :: OSI Approved :: GNU Affero General Public License v3
Classifier: Operating System :: OS Independent
Classifier: Programming Language :: Python :: 3
Classifier: Programming Language :: Python :: 3.9
Classifier: Programming Language :: Python :: 3.10
Classifier: Programming Language :: Python :: 3.11
Classifier: Programming Language :: Python :: 3.12
Classifier: Programming Language :: Python :: 3.13
Classifier: Topic :: Internet :: WWW/HTTP
Classifier: Topic :: Software Development :: Libraries :: Python Modules
Project-URL: Homepage, https://github.com/pelican-plugins/seo
Project-URL: Issue Tracker, https://github.com/pelican-plugins/seo/issues
Project-URL: Changelog, https://github.com/pelican-plugins/seo/blob/main/CHANGELOG.md
Project-URL: Funding, https://donate.getpelican.com/
Requires-Python: ~=3.9
Requires-Dist: pelican>=4.5
Requires-Dist: beautifulsoup4>=4.9
Provides-Extra: markdown
Requires-Dist: markdown>=3.4; extra == "markdown"
